oaiharvest/__init__.py
oaiharvest/exceptions.py
oaiharvest/harvest.py
oaiharvest/metadata.py
oaiharvest/registry.py
oaiharvest/test/__init__.py
oaiharvest/test/test_harvest.py
oaiharvest-3.0.0.dist-info/DESCRIPTION.rst
oaiharvest-3.0.0.dist-info/METADATA
oaiharvest-3.0.0.dist-info/RECORD
oaiharvest-3.0.0.dist-info/WHEEL
oaiharvest-3.0.0.dist-info/entry_points.txt
oaiharvest-3.0.0.dist-info/metadata.json
oaiharvest-3.0.0.dist-info/top_level.txt
