Metadata-Version: 2.0
Name: oaiharvest
Version: 3.0.0
Summary: A harvester to collect records from an OAI-PMH enabled provider.
Home-page: http://github.com/bloomonkey/oai-harvest
Author: John Harrison
Author-email: john@bloomonkey.co.uk
License: BSD
Platform: UNKNOWN
Classifier: Intended Audience :: Developers
Classifier: Intended Audience :: Information Technology
Classifier: License :: OSI Approved :: BSD License
Classifier: Programming Language :: Python :: 2.7
Classifier: Programming Language :: Python :: 3.4
Classifier: Programming Language :: Python :: 3.5
Classifier: Programming Language :: Python :: 3.6
Classifier: Topic :: Text Processing :: Markup
Requires: lxml(>=2.1)
Requires: pyoai(>=2.4)
Requires-Dist: lxml (>=2.1)
Requires-Dist: mock (>=2.0.0)
Requires-Dist: pyoai (>=2.4)
Requires-Dist: six (>=1.0)
Requires-Dist: setuptools (>=35.0.1)
Requires-Dist: argparse; python_version=="2.6"
Requires-Dist: argparse; python_version=="2.7"
